{
  "type": "object",
  "properties": {
    "currentPeriod": {
      "type": "object",
      "properties": {
        "startDate": { "type": "string", "example": "2026-05-17T00:00:00.000Z" },
        "endDate": { "type": "string", "example": "2026-05-17T00:00:00.000Z" },
        "description": { "type": "string" }
      },
      "required": ["startDate", "endDate", "description"]
    },
    "totalIncome": { "type": "number" },
    "totalExpenses": { "type": "number" },
    "monthlyIncome": { "type": "number" },
    "balance": { "type": "number" },
    "percentUsed": { "type": "number", "nullable": true },
    "byCategory": { "type": "object", "additionalProperties": { "type": "number" } },
    "alert": { "type": "string", "nullable": true },
    "transactionsCount": { "type": "integer" }
  },
  "required": [
    "currentPeriod",
    "totalIncome",
    "totalExpenses",
    "monthlyIncome",
    "balance",
    "percentUsed",
    "byCategory",
    "alert",
    "transactionsCount"
  ],
  "x-readme-ref-name": "CurrentPeriodSummary"
}
